add_classifiers/__init__.py
add_classifiers-0.3.0.dist-info/WHEEL
add_classifiers-0.3.0.dist-info/entry_points.txt
add_classifiers-0.3.0.dist-info/METADATA
add_classifiers-0.3.0.dist-info/RECORD
